{"type":"FeatureCollection", "features":[
{"type":"Feature","id":"0F3051602333336FAE10","geometry":{"type":"Point","coordinates":[45.90571327456175,39.53461770005973,1905.350251154683]},"properties":{"0DABDD2EAF33336FAE42":0,"name":"Məzrə","extrude":true}}
]}
